stactools/aster/__init__.py
stactools/aster/cog.py
stactools/aster/commands.py
stactools/aster/constants.py
stactools/aster/stac.py
stactools/aster/utils.py
stactools/aster/xml_metadata.py
stactools_aster-0.2.1.dist-info/LICENSE
stactools_aster-0.2.1.dist-info/METADATA
stactools_aster-0.2.1.dist-info/WHEEL
stactools_aster-0.2.1.dist-info/top_level.txt
stactools_aster-0.2.1.dist-info/RECORD
