Metadata-Version: 2.1
Name: stactools-aster
Version: 0.2.1
Summary: PROVIDE DESCRIPTION HERE
Home-page: https://github.com/stactools-asters/stactools-aster
Author: stac-utils
Author-email: stac@radiant.earth
Project-URL: Documentation, https://stactools-aster.readthedocs.io/en/latest/
Project-URL: Issues, https://github.com/stactools-asters/stactools-aster/issues
Keywords: stactools,pystac,catalog,STAC
Classifier: Development Status :: 4 - Beta
Classifier: License :: OSI Approved :: Apache Software License
Classifier: Programming Language :: Python :: 3.7
Classifier: Programming Language :: Python :: 3.8
Classifier: Programming Language :: Python :: 3.9
License-File: LICENSE
Requires-Dist: stactools (>=0.4.2)
Requires-Dist: shapely (<2)
